bingqilin/__init__.py
bingqilin/__main__.py
bingqilin/conf/__init__.py
bingqilin/conf/models.py
bingqilin/conf/openapi.py
bingqilin/conf/sources.py
bingqilin/contexts.py
bingqilin/db/__init__.py
bingqilin/db/models.py
bingqilin/db/redis.py
bingqilin/db/sqlalchemy.py
bingqilin/extras/__init__.py
bingqilin/extras/aws/__init__.py
bingqilin/extras/aws/conf/__init__.py
bingqilin/extras/aws/conf/sources.py
bingqilin/extras/aws/conf/types.py
bingqilin/handlers.py
bingqilin/logger.py
bingqilin/management/__init__.py
bingqilin/management/base.py
bingqilin/management/cli.py
bingqilin/management/commands/__init__.py
bingqilin/management/commands/shell.py
bingqilin/management/context.py
bingqilin/management/init_shell.py
bingqilin/management/logging.py
bingqilin/management/utils.py
bingqilin/signal.py
bingqilin/utils/__init__.py
bingqilin/utils/dict.py
bingqilin/utils/types.py
bingqilin-0.6.6.dist-info/LICENSE
bingqilin-0.6.6.dist-info/METADATA
bingqilin-0.6.6.dist-info/WHEEL
bingqilin-0.6.6.dist-info/entry_points.txt
bingqilin-0.6.6.dist-info/RECORD
