Metadata-Version: 2.3
Name: bingqilin
Version: 0.6.6
Summary: A collection of utilities for building APIs with FastAPI
License: MIT
Keywords: bingqilin,fastapi
Author: Andy
Author-email: andy@ahn.io
Requires-Python: >=3.9
Classifier: License :: OSI Approved :: MIT License
Classifier: Programming Language :: Python :: 3
Classifier: Programming Language :: Python :: 3.9
Classifier: Programming Language :: Python :: 3.10
Classifier: Programming Language :: Python :: 3.11
Classifier: Programming Language :: Python :: 3.12
Classifier: Programming Language :: Python :: 3.13
Provides-Extra: management
Requires-Dist: deprecated (>=1.2.14)
Requires-Dist: fastapi (>=0.95.2,<1.0.0)
Requires-Dist: pydantic (>=2.2.2)
Requires-Dist: pydantic-settings (>=2.0.3)
Requires-Dist: pyyaml (>=6.0.1)
Requires-Dist: typer ; extra == "management"
